gradle.properties
hexdoc_lapisworks/__gradle_version__.py
hexdoc_lapisworks/__init__.py
hexdoc_lapisworks/__version__.py
hexdoc_lapisworks/_hooks.py
hexdoc_lapisworks/py.typed
hexdoc_lapisworks/_export/.gitignore
hexdoc_lapisworks/_export/__init__.py
hexdoc_lapisworks/_export/generated/__init__.py
hexdoc_lapisworks/_export/generated/lapisworks.hexdoc.json
hexdoc_lapisworks/_export/generated/lapisworks.patterns.hexdoc.json
hexdoc_lapisworks/_export/generated/assets/hexcasting/patchouli_books/thehexbook/en_us/categories/lapisworks.json
hexdoc_lapisworks/_export/generated/assets/hexcasting/patchouli_books/thehexbook/en_us/categories/lapisworks/great.json
hexdoc_lapisworks/_export/generated/assets/hexcasting/patchouli_books/thehexbook/en_us/categories/lapisworks/imbuement.json
hexdoc_lapisworks/_export/generated/assets/hexcasting/patchouli_books/thehexbook/en_us/categories/lapisworks/interop.json
hexdoc_lapisworks/_export/generated/assets/hexcasting/patchouli_books/thehexbook/en_us/entries/lapisworks_great.json
hexdoc_lapisworks/_export/generated/assets/hexcasting/patchouli_books/thehexbook/en_us/entries/lapisworks_lore.json
hexdoc_lapisworks/_export/generated/assets/hexcasting/patchouli_books/thehexbook/en_us/entries/lapisworks_misc.json
hexdoc_lapisworks/_export/generated/assets/hexcasting/patchouli_books/thehexbook/en_us/entries/lapisworks_mishaps.json
hexdoc_lapisworks/_export/generated/assets/hexcasting/patchouli_books/thehexbook/en_us/entries/lapisworks_patterns.json
hexdoc_lapisworks/_export/generated/assets/hexcasting/patchouli_books/thehexbook/en_us/entries/lapisworks_placeholder.json
hexdoc_lapisworks/_export/generated/assets/hexcasting/patchouli_books/thehexbook/en_us/entries/great/collectsomeshitfam.json
hexdoc_lapisworks/_export/generated/assets/hexcasting/patchouli_books/thehexbook/en_us/entries/great/enchsent.json
hexdoc_lapisworks/_export/generated/assets/hexcasting/patchouli_books/thehexbook/en_us/entries/great/flay_artmind.json
hexdoc_lapisworks-1.5.6.9.1.6.dev0.dist-info/METADATA
hexdoc_lapisworks-1.5.6.9.1.6.dev0.dist-info/WHEEL
hexdoc_lapisworks-1.5.6.9.1.6.dev0.dist-info/entry_points.txt
hexdoc_lapisworks-1.5.6.9.1.6.dev0.dist-info/licenses/LICENSE
hexdoc_lapisworks-1.5.6.9.1.6.dev0.dist-info/RECORD
