Metadata-Version: 2.4
Name: hexdoc-lapisworks
Version: 1.5.6.9.1.6.dev0
Summary: Python web book docgen and hexdoc plugin for Lapisworks.
Project-URL: Homepage, https://real-luxof.github.io/Lapisworks/
Project-URL: Source, https://github.com/Real-Luxof/Lapisworks
Author: Real-Luxof
License-File: LICENSE
Keywords: hexdoc
Requires-Python: >=3.11
Requires-Dist: hexdoc-hexcasting~=0.11.2.1.0
Requires-Dist: hexdoc~=1!0.1.0a11
Requires-Dist: networkx~=3.5
Requires-Dist: scipy~=1.16
Provides-Extra: dev
Requires-Dist: ruff~=0.11.2; extra == 'dev'
